block_cascade/__init__.py
block_cascade/concurrency/__init__.py
block_cascade/config.py
block_cascade/consts.py
block_cascade/decorators.py
block_cascade/executors/__init__.py
block_cascade/executors/databricks/__init__.py
block_cascade/executors/databricks/executor.py
block_cascade/executors/databricks/filesystem.py
block_cascade/executors/databricks/job.py
block_cascade/executors/databricks/resource.py
block_cascade/executors/databricks/run.py
block_cascade/executors/executor.py
block_cascade/executors/local/__init__.py
block_cascade/executors/local/executor.py
block_cascade/executors/vertex/__init__.py
block_cascade/executors/vertex/distributed/__init__.py
block_cascade/executors/vertex/distributed/distributed_job.py
block_cascade/executors/vertex/distributed/torch_job.py
block_cascade/executors/vertex/distributed/torchrun_target.py
block_cascade/executors/vertex/executor.py
block_cascade/executors/vertex/job.py
block_cascade/executors/vertex/resource.py
block_cascade/executors/vertex/run.py
block_cascade/executors/vertex/tune.py
block_cascade/gcp/__init__.py
block_cascade/gcp/monitoring.py
block_cascade/prefect/__init__.py
block_cascade/prefect/v1/__init__.py
block_cascade/prefect/v1/environment.py
block_cascade/prefect/v2/__init__.py
block_cascade/prefect/v2/environment.py
block_cascade/prefect/v3/__init__.py
block_cascade/prefect/v3/environment.py
block_cascade/utils.py
block_cascade-3.1.0.dist-info/METADATA
block_cascade-3.1.0.dist-info/WHEEL
block_cascade-3.1.0.dist-info/entry_points.txt
block_cascade-3.1.0.dist-info/licenses/LICENSE.txt
block_cascade-3.1.0.dist-info/RECORD
