Metadata-Version: 2.4
Name: block-cascade
Version: 3.1.0
Summary: Library for model training in multi-cloud environment.
License-File: LICENSE.txt
Author: Block
Requires-Python: >=3.9,<3.13
Classifier: Programming Language :: Python :: 3
Classifier: Programming Language :: Python :: 3.9
Classifier: Programming Language :: Python :: 3.10
Classifier: Programming Language :: Python :: 3.11
Classifier: Programming Language :: Python :: 3.12
Requires-Dist: cloudml-hypertune (==0.1.0.dev6)
Requires-Dist: cloudpickle (>=2.0,<3.0)
Requires-Dist: databricks-cli (>=0.17.7)
Requires-Dist: gcsfs (>=2024)
Requires-Dist: google-auth (>=2.23.2,<3.0.0)
Requires-Dist: google-cloud-aiplatform (>=1.39.0,<2.0.0)
Requires-Dist: google-cloud-monitoring (>=2.16.0,<3.0.0)
Requires-Dist: google-cloud-resource-manager (>=1.10.4,<2.0.0)
Requires-Dist: importlib_resources ; python_version < "3.9"
Requires-Dist: prefect (>=2.0,<4.0.0)
Requires-Dist: pydantic (>=2.0.0,<3.0.0)
Requires-Dist: s3fs (>=2024)
